Workbook
Name aporte: Investimentos!$D$17
Name qtd_anos: Investimentos!$D$18
Name rendimento_carteira: Investimentos!$D$13
Name salario: Investimentos!$D$12
Name sugestao_investimento: Investimentos!$D$14
Name taxa_mensal: Investimentos!$D$19

Sheet Investimentos
B11: CONFIGURAÇÕES
B12: Salário | D12: 2000
B13: Rendimento de Carteira | D13: 0.01079
B14: Sugestão de investimento (30%) | D14: =D12*30% -> 600
B16: INVESTIMENTO MENSAL
B17: Quanto investir por mês? | D17: 600
B18: Por quantos Anos? | D18: 10
B19: Taxa de rendimento mensal? | D19: =rendimento_carteira -> 0.01079
B20: Patrimônio acumulado? | D20: =FV(taxa_mensal,qtd_anos*12,aporte*-1) -> 145970.53
B21: Dividendos mensais? | D21: =D20*$D$13 -> 1575.022
B24: CENÁRIOS | D24: DIVIDENDOS
A25: 2 | B25: Quanto em 2 anos? | C25: =FV($D$19,$A25*12,$D$17*-1) -> 16336.576 | D25: =C25*rendimento_carteira -> 176.27166
A26: 5 | B26: Quanto em 5 anos? | C26: =FV($D$19,$A26*12,$D$17*-1) -> 50266.148 | D26: =C26*rendimento_carteira -> 542.37174
A27: 10 | B27: Quanto em 10 anos? | C27: =FV($D$19,$A27*12,$D$17*-1) -> 145970.53 | D27: =C27*rendimento_carteira -> 1575.022
A28: 15 | B28: Quanto em 15 anos? | C28: =FV($D$19,$A28*12,$D$17*-1) -> 328187.16 | D28: =C28*rendimento_carteira -> 3541.1394
A29: 20 | B29: Quanto em 20 anos? | C29: =FV($D$19,$A29*12,$D$17*-1) -> 675119.04 | D29: =C29*rendimento_carteira -> 7284.5344
A30: 30 | B30: Quanto em 30 anos? | C30: =FV($D$19,$A30*12,$D$17*-1) -> 2593301.8 | D30: =C30*rendimento_carteira -> 27981.726
B32: PERFIL DE INVESTIMENTO | C32: Moderado
B33: VALOR A SER INVESTIDO POR MÊS | C33: =aporte -> 600
B35: TIPOS DE FII | C35: PERCENTUAL SUGERIDO | D35: VALORES
B36: PAPEL | C36: =VLOOKUP($C$32&"-"&B36,Planilha2!$A$2:$D$20,4,FALSE) -> 0.32 | D36: =C36*$C$33 -> 192
B37: TIJOLO | C37: =VLOOKUP($C$32&"-"&B37,Planilha2!$A$2:$D$20,4,FALSE) -> 0.35 | D37: =C37*$C$33 -> 210
B38: HÍBRIDOS | C38: =VLOOKUP($C$32&"-"&B38,Planilha2!$A$2:$D$20,4,FALSE) -> 0.08 | D38: =C38*$C$33 -> 48
B39: FOFs | C39: =VLOOKUP($C$32&"-"&B39,Planilha2!$A$2:$D$20,4,FALSE) -> 0.05 | D39: =C39*$C$33 -> 30
B40: DESENVOLVIMENTO | C40: =VLOOKUP($C$32&"-"&B40,Planilha2!$A$2:$D$20,4,FALSE) -> 0.1 | D40: =C40*$C$33 -> 60
B41: HOTELARIAS | C41: =VLOOKUP($C$32&"-"&B41,Planilha2!$A$2:$D$20,4,FALSE) -> 0.1 | D41: =C41*$C$33 -> 60
D42: =SUM(D36:D41) -> 600

Sheet Planilha2
A2: CHAVE | B2: PERFIL | C2: TIPO DE FII | D2: %
A3: =B3&"-"&C3 -> Conservador-PAPEL | B3: Conservador | C3: PAPEL | D3: 0.3
A4: =B4&"-"&C4 -> Conservador-TIJOLO | B4: Conservador | C4: TIJOLO | D4: 0.5
A5: =B5&"-"&C5 -> Conservador-HÍBRIDOS | B5: Conservador | C5: HÍBRIDOS | D5: 0.1
A6: =B6&"-"&C6 -> Conservador-FOFs | B6: Conservador | C6: FOFs | D6: 0.1
A7: =B7&"-"&C7 -> Conservador-DESENVOLVIMENTO | B7: Conservador | C7: DESENVOLVIMENTO | D7: 0
A8: =B8&"-"&C8 -> Conservador-HOTELARIAS | B8: Conservador | C8: HOTELARIAS | D8: 0
A9: =B9&"-"&C9 -> Moderado-PAPEL | B9: Moderado | C9: PAPEL | D9: 0.32
A10: =B10&"-"&C10 -> Moderado-TIJOLO | B10: Moderado | C10: TIJOLO | D10: 0.35
A11: =B11&"-"&C11 -> Moderado-HÍBRIDOS | B11: Moderado | C11: HÍBRIDOS | D11: 0.08
A12: =B12&"-"&C12 -> Moderado-FOFs | B12: Moderado | C12: FOFs | D12: 0.05
A13: =B13&"-"&C13 -> Moderado-DESENVOLVIMENTO | B13: Moderado | C13: DESENVOLVIMENTO | D13: 0.1
A14: =B14&"-"&C14 -> Moderado-HOTELARIAS | B14: Moderado | C14: HOTELARIAS | D14: 0.1
... A20: =B20&"-"&C20 -> Agressivo-HOTELARIAS | B20: Agressivo | C20: HOTELARIAS | D20: 0.1
